.eslintrc.json
.prettierrc.json
.stylelintrc.json
CHANGES.rst
CONTRIBUTORS.rst
DEVELOP.rst
LICENSE.GPL
LICENSE.rst
MANIFEST.in
README.rst
constraints.txt
constraints_plone51.txt
constraints_plone52.txt
package.json
postcss.config.js
requirements.txt
setup.cfg
setup.py
webpack.config.js
yarn.lock
docs/conf.py
docs/index.rst
src/collective/__init__.py
src/collective.z3cform.jsonwidget.egg-info/PKG-INFO
src/collective.z3cform.jsonwidget.egg-info/SOURCES.txt
src/collective.z3cform.jsonwidget.egg-info/dependency_links.txt
src/collective.z3cform.jsonwidget.egg-info/entry_points.txt
src/collective.z3cform.jsonwidget.egg-info/namespace_packages.txt
src/collective.z3cform.jsonwidget.egg-info/not-zip-safe
src/collective.z3cform.jsonwidget.egg-info/requires.txt
src/collective.z3cform.jsonwidget.egg-info/top_level.txt
src/collective/z3cform/__init__.py
src/collective/z3cform/jsonwidget/__init__.py
src/collective/z3cform/jsonwidget/configure.zcml
src/collective/z3cform/jsonwidget/interfaces.py
src/collective/z3cform/jsonwidget/permissions.zcml
src/collective/z3cform/jsonwidget/setuphandlers.py
src/collective/z3cform/jsonwidget/testing.py
src/collective/z3cform/jsonwidget/browser/__init__.py
src/collective/z3cform/jsonwidget/browser/configure.zcml
src/collective/z3cform/jsonwidget/browser/json_widget_input.pt
src/collective/z3cform/jsonwidget/browser/widget.py
src/collective/z3cform/jsonwidget/browser/static/dist/prod/main.css
src/collective/z3cform/jsonwidget/browser/static/dist/prod/main.css.map
src/collective/z3cform/jsonwidget/browser/static/dist/prod/main.js
src/collective/z3cform/jsonwidget/browser/static/dist/prod/main.js.map
src/collective/z3cform/jsonwidget/browser/static/js/index.js
src/collective/z3cform/jsonwidget/browser/static/js/ArrayFieldContainer/index.js
src/collective/z3cform/jsonwidget/browser/static/js/EntryColumnContainer/index.js
src/collective/z3cform/jsonwidget/browser/static/js/EntryColumnContainer/index.less
src/collective/z3cform/jsonwidget/browser/static/js/WidgetContainer/index.js
src/collective/z3cform/jsonwidget/browser/static/js/WidgetDataContainer/index.js
src/collective/z3cform/jsonwidget/browser/static/js/WidgetDataContainer/index.less
src/collective/z3cform/jsonwidget/browser/static/js/fields/LinesField.js
src/collective/z3cform/jsonwidget/browser/static/js/fields/LinesField.less
src/collective/z3cform/jsonwidget/browser/static/js/fields/ReferenceField.js
