Metadata-Version: 2.1
Name: collective.z3cform.jsonwidget
Version: 1.1.1
Summary: Custom widget to manage complex json data stored into a text field
Home-page: https://github.com/collective/collective.z3cform.jsonwidget
Author: Andrea Cecchi
Author-email: andrea.cecchi85@gmail.com
License: GPL version 2
Project-URL: PyPI, https://pypi.python.org/pypi/collective.z3cform.jsonwidget
Project-URL: Source, https://github.com/collective/collective.z3cform.jsonwidget
Project-URL: Tracker, https://github.com/collective/collective.z3cform.jsonwidget/issues
Keywords: Python Plone
Platform: UNKNOWN
Classifier: Environment :: Web Environment
Classifier: Framework :: Plone
Classifier: Framework :: Plone :: Addon
Classifier: Framework :: Plone :: 5.2
Classifier: Programming Language :: Python
Classifier: Programming Language :: Python :: 2.7
Classifier: Programming Language :: Python :: 3.6
Classifier: Programming Language :: Python :: 3.7
Classifier: Operating System :: OS Independent
Classifier: License :: OSI Approved :: GNU General Public License v2 (GPLv2)
Requires-Python: ==2.7, >=3.6
Provides-Extra: test
